day_equity_fyers_historical/__init__.py
day_equity_fyers_historical/A1_auth_access_and_refresh_token.py
day_equity_fyers_historical/A2_loguru_and_telegram_combine.py
day_equity_fyers_historical/A3_CSV_dates_symbols_name_getting.py
day_equity_fyers_historical/A4_historical_downloader.py
day_equity_fyers_historical/A5_append_ohlc_old_and_new.py
day_equity_fyers_historical/A6_main.py
day_equity_fyers_historical/last_date.txt
day_equity_fyers_historical/Logs/logs_2024-07-20.csv
day_equity_fyers_historical/symbols_list.txt
day_equity_fyers_historical-0.1.0.dist-info/METADATA
day_equity_fyers_historical-0.1.0.dist-info/WHEEL
day_equity_fyers_historical-0.1.0.dist-info/RECORD
