Metadata-Version: 2.1
Name: day-equity-fyers-historical
Version: 0.1.0
Summary: 
Author: Your Name
Author-email: you@example.com
Requires-Python: >=3.11,<4.0
Classifier: Programming Language :: Python :: 3
Classifier: Programming Language :: Python :: 3.11
Classifier: Programming Language :: Python :: 3.12
Requires-Dist: datetime (>=5.5,<6.0)
Requires-Dist: fyers-apiv3 (>=3.1.2,<4.0.0)
Requires-Dist: loguru (>=0.7.2,<0.8.0)
Requires-Dist: polars (>=1.2.1,<2.0.0)
Requires-Dist: python-dotenv (>=1.0.1,<2.0.0)
